<Properties StartupConfiguration="{9C82FD55-770B-4E6D-A17A-10AB4EAC3040}|Default">
  <MonoDevelop.Ide.Workbench ActiveDocument="Program.cs">
    <Files>
      <File FileName="Program.cs" Line="20" Column="46" />
    </Files>
    <Pads>
      <Pad Id="ProjectPad">
        <State name="__root__">
          <Node name="ExerciseTwoThree" expanded="True">
            <Node name="ExerciseTwoThree" expanded="True">
              <Node name="Program.cs" selected="True" />
            </Node>
          </Node>
        </State>
      </Pad>
    </Pads>
  </MonoDevelop.Ide.Workbench>
  <MonoDevelop.Ide.DebuggingService.PinnedWatches />
  <MonoDevelop.Ide.Workspace ActiveConfiguration="Debug" />
  <MonoDevelop.Ide.DebuggingService.Breakpoints>
    <BreakpointStore />
  </MonoDevelop.Ide.DebuggingService.Breakpoints>
  <MultiItemStartupConfigurations />
  <MonoDevelop.Ide.ItemProperties.ExerciseTwoThree PreferredExecutionTarget="MonoDevelop.Default" />
</Properties>